{
	"credit": "Made with Blockbench",
	"texture_size": [18, 22],
	"textures": {
		"0": "milkevsoreminers:block/sifter",
		"1": "block/oak_planks",
		"particle": "milkevsoreminers:block/sifter"
	},
	"elements": [
		{
			"name": "LNE",
			"from": [14, 0, 0],
			"to": [16, 11, 2],
			"faces": {
				"north": {"uv": [14.22222, 0, 16, 8], "texture": "#0"},
				"east": {"uv": [14.22222, 0, 16, 8], "texture": "#0"},
				"south": {"uv": [14.22222, 0, 16, 8], "texture": "#0"},
				"west": {"uv": [14.22222, 0, 16, 8], "texture": "#0"},
				"up": {"uv": [14.22222, 13.81818, 16, 15.27273], "texture": "#0"},
				"down": {"uv": [14.22222, 8, 16, 9.45455], "texture": "#0"}
			}
		},
		{
			"name": "LSW",
			"from": [0, 0, 14],
			"to": [2, 11, 16],
			"faces": {
				"north": {"uv": [14.22222, 0, 16, 8], "texture": "#0"},
				"east": {"uv": [14.22222, 0, 16, 8], "texture": "#0"},
				"south": {"uv": [14.22222, 0, 16, 8], "texture": "#0"},
				"west": {"uv": [14.22222, 0, 16, 8], "texture": "#0"},
				"up": {"uv": [14.22222, 13.81818, 16, 15.27273], "texture": "#0"},
				"down": {"uv": [14.22222, 8, 16, 9.45455], "texture": "#0"}
			}
		},
		{
			"name": "LNW",
			"from": [0, 0, 0],
			"to": [2, 11, 2],
			"faces": {
				"north": {"uv": [14.22222, 0, 16, 8], "texture": "#0"},
				"east": {"uv": [14.22222, 0, 16, 8], "texture": "#0"},
				"south": {"uv": [14.22222, 0, 16, 8], "texture": "#0"},
				"west": {"uv": [14.22222, 0, 16, 8], "texture": "#0"},
				"up": {"uv": [14.22222, 13.81818, 16, 15.27273], "texture": "#0"},
				"down": {"uv": [14.22222, 8, 16, 9.45455], "texture": "#0"}
			}
		},
		{
			"name": "LSE",
			"from": [14, 0, 14],
			"to": [16, 11, 16],
			"faces": {
				"north": {"uv": [14.22222, 0, 16, 8], "texture": "#0"},
				"east": {"uv": [14.22222, 0, 16, 8], "texture": "#0"},
				"south": {"uv": [14.22222, 0, 16, 8], "texture": "#0"},
				"west": {"uv": [14.22222, 0, 16, 8], "texture": "#0"},
				"up": {"uv": [14.22222, 13.81818, 16, 15.27273], "texture": "#0"},
				"down": {"uv": [14.22222, 8, 16, 9.45455], "texture": "#0"}
			}
		},
		{
			"name": "TW",
			"from": [0, 11, 0],
			"to": [2, 14, 16],
			"faces": {
				"north": {"uv": [12.44444, 11.63636, 14.22222, 13.81818], "texture": "#0"},
				"east": {"uv": [0, 13.81818, 14.22222, 16], "texture": "#0"},
				"south": {"uv": [0, 11.63636, 1.77778, 13.81818], "texture": "#0"},
				"west": {"uv": [0, 11.63636, 14.22222, 13.81818], "texture": "#0"},
				"up": {"uv": [0, 0, 1.77778, 11.63636], "texture": "#0"},
				"down": {"uv": [0.88889, 12.36364, 15.11111, 13.81818], "rotation": 90, "texture": "#0"}
			}
		},
		{
			"name": "TE",
			"from": [14, 11, 0],
			"to": [16, 14, 16],
			"faces": {
				"north": {"uv": [0, 11.63636, 1.77778, 13.81818], "texture": "#0"},
				"east": {"uv": [0, 0, 15, 2.18182], "texture": "#1"},
				"south": {"uv": [12.44444, 11.63636, 14.22222, 13.81818], "texture": "#0"},
				"west": {"uv": [0, 13.81818, 14.22222, 16], "texture": "#0"},
				"up": {"uv": [12.44444, 0, 14.22222, 11.63636], "texture": "#0"},
				"down": {"uv": [1.77778, 11.63636, 16, 13.09091], "rotation": 90, "texture": "#0"}
			}
		},
		{
			"name": "TN",
			"from": [2, 11, 0],
			"to": [14, 14, 2],
			"faces": {
				"north": {"uv": [1.77778, 11.63636, 12.44444, 13.81818], "texture": "#0"},
				"east": {"uv": [0, 0, 10.66667, 2.18182], "texture": "#0"},
				"south": {"uv": [1.77778, 13.81818, 12.44444, 16], "texture": "#0"},
				"west": {"uv": [0, 0, 10.66667, 2.18182], "texture": "#0"},
				"up": {"uv": [1.77778, 0, 12.44444, 1.45455], "texture": "#0"},
				"down": {"uv": [0, 11.63636, 10.66667, 13.09091], "rotation": 180, "texture": "#0"}
			}
		},
		{
			"name": "TS",
			"from": [2, 11, 14],
			"to": [14, 14, 16],
			"faces": {
				"north": {"uv": [1.77778, 13.81818, 12.44444, 16], "texture": "#0"},
				"east": {"uv": [0, 0, 10.66667, 2.18182], "texture": "#0"},
				"south": {"uv": [1.77778, 11.63636, 12.44444, 13.81818], "texture": "#1"},
				"west": {"uv": [0, 0, 10.66667, 2.18182], "texture": "#0"},
				"up": {"uv": [1.77778, 10.18182, 12.44444, 11.63636], "texture": "#0"},
				"down": {"uv": [0, 11.63636, 10.66667, 13.09091], "texture": "#0"}
			}
		},
		{
			"name": "TNET",
			"from": [2, 12, 2],
			"to": [14, 12, 14],
			"faces": {
				"up": {"uv": [2.66667, 1.45455, 12.44444, 9.45455], "texture": "#0"},
				"down": {"uv": [12.44444, 1.45455, 2.66667, 9.45455], "rotation": 180, "texture": "#0"}
			}
		}
	]
}